worlddatafilter/__init__.py
worlddatafilter/cli.py
worlddatafilter/core.py
worlddatafilter/loaders.py
worlddatafilter/types.py
worlddatafilter/utils.py
worlddatafilter/extractors/base.py
worlddatafilter/selectors/facility.py
worlddatafilter/selectors/novelty.py
worlddatafilter/selectors/quality.py
worlds_data_filter-0.1.1.dist-info/licenses/LICENSE
worlds_data_filter-0.1.1.dist-info/METADATA
worlds_data_filter-0.1.1.dist-info/WHEEL
worlds_data_filter-0.1.1.dist-info/entry_points.txt
worlds_data_filter-0.1.1.dist-info/top_level.txt
worlds_data_filter-0.1.1.dist-info/RECORD
