Metadata-Version: 2.4
Name: worlds-data-filter
Version: 0.1.1
Summary: The World's Data Filter — find the most valuable data, first with a universal SDK/CLI that ranks, filters, and subsets heterogeneous data by information gain, novelty, and quality.
Author: The World's Data Company
License: Apache License
Project-URL: Homepage, https://worlddatafilter.com
Project-URL: Source, https://github.com/worlddataco/worlds-data-filter
Keywords: data,filter,information gain,subset selection,RAG,ETL,quality
Classifier: Programming Language :: Python :: 3
Classifier: License :: OSI Approved :: Apache Software License
Classifier: Intended Audience :: Developers
Classifier: Topic :: Scientific/Engineering :: Information Analysis
Requires-Python: >=3.10
License-File: LICENSE
Requires-Dist: numpy>=1.24
Requires-Dist: scipy>=1.10
Requires-Dist: pydantic>=2.4
Requires-Dist: pydantic-settings>=2.0
Requires-Dist: typer>=0.12
Requires-Dist: orjson>=3.9
Provides-Extra: text
Requires-Dist: scikit-learn>=1.3; extra == "text"
Provides-Extra: api
Requires-Dist: fastapi>=0.110; extra == "api"
Requires-Dist: uvicorn[standard]>=0.23; extra == "api"
Provides-Extra: dev
Requires-Dist: ruff>=0.5; extra == "dev"
Requires-Dist: pytest>=7.4; extra == "dev"
Requires-Dist: pytest-cov>=4.1; extra == "dev"
Requires-Dist: pre-commit>=3.5; extra == "dev"
Requires-Dist: mypy>=1.8; extra == "dev"
Dynamic: license-file
